mpralib/__init__.py
mpralib/cli.py
mpralib/exception.py
mpralib/mpradata.py
mpralib/data/hg19.chromAlias.txt
mpralib/data/hg38.chromAlias.txt
mpralib/utils/__init__.py
mpralib/utils/file_validation.py
mpralib/utils/io.py
mpralib/utils/plot.py
mpralib-0.9.1.dist-info/licenses/LICENSE
mpralib-0.9.1.dist-info/METADATA
mpralib-0.9.1.dist-info/WHEEL
mpralib-0.9.1.dist-info/entry_points.txt
mpralib-0.9.1.dist-info/top_level.txt
mpralib-0.9.1.dist-info/RECORD
