Metadata-Version: 2.4
Name: mpralib
Version: 0.9.1
Summary: Library to analyze count data of MPRA experiments.
Home-page: https://github.com/kircherlab/MPRAlib
Author: Max Schubach
Author-email: Max Schubach <max.schubach@bih-charite.de>
Classifier: Programming Language :: Python :: 3
Classifier: License :: OSI Approved :: MIT License
Classifier: Operating System :: OS Independent
Requires-Python: >=3.9
License-File: LICENSE
Requires-Dist: numpy
Requires-Dist: pandas
Requires-Dist: pysam
Requires-Dist: click
Requires-Dist: scikit-learn
Requires-Dist: scipy
Requires-Dist: anndata>=0.11.3
Requires-Dist: seaborn
Requires-Dist: matplotlib
Requires-Dist: jsonschema
Requires-Dist: tqdm
Provides-Extra: test
Requires-Dist: pytest; extra == "test"
Requires-Dist: coverage; extra == "test"
Dynamic: author
Dynamic: classifier
Dynamic: home-page
Dynamic: license-file
Dynamic: requires-dist
Dynamic: requires-python
Dynamic: summary
